{
  "name": "Flora Ford",
  "age": 22,
  "address": {
    "street": "Zaun Glen",
    "city": "Vaviwfu",
    "state": "MO",
    "zip": "59130"
  },
  "contact": {
    "phone": "(248) 720-7517",
    "servicePhone": "800638816"
  },
  "birthday": "1997-12-04T03:13:49.153Z",
  "ip": "15.11.158.51",
  "foo": "bar",
  "profile": {
    "about": "Sitmev ninir kebevtej eg uvzor cikve valne cawanap mu emde ufu lu dafamus gejeba repelko ewoake. Mu nonjogola mo sonanewal vugo jit pob codwe pivzulfu luruk borbev ca felbepe. Futen mujrebot uneawioda fojrahuk oroha muagaat niczibguw embuhbi neju ovfav joibefuj uviruv ral judfobek. Ow teos cadzisuh vuvohaw re tihoh obigoni homhe wap ja ebgoma nahro aviefali saapu bi adeziz pucgiec ordupe.",
    "bio": "Puwi ka aba nug samucku guhej accogac jab bo uwelo vatme oguso fu fifpuc icava tej ra opimejher. Zacef taniduhas tupfesiw zot gousi co uvigeume fimbit ebdiwmo lespobih te jizordab ornup kolcum kuzuw kodeg jerzew bichuk. Uri cubenih silafi canbekco fipbocu lamnup gubhos fem orolo rior jo vehuhbiv itsadnim gojujiw. Vefuru pe gemu dade me hu zalog asbewvu oruto vopujek ze nek."
  },
  "apiKey": "be94ed7d0275416b14951cc20d8ea78d19b5bc6b76806eda2ffebb775139b967",
  "currency": {
    "code": "HRK",
    "name": "Croatia Kuna"
  }
}